outcache/__init__.py
outcache/cachable.py
outcache/cache.py
outcache/cache_async.py
OutCache-1.0.1.dist-info/LICENSE
OutCache-1.0.1.dist-info/METADATA
OutCache-1.0.1.dist-info/WHEEL
OutCache-1.0.1.dist-info/top_level.txt
OutCache-1.0.1.dist-info/RECORD
