Metadata-Version: 2.1
Name: OutCache
Version: 1.0.1
Summary: Function output cacher
Home-page: https://github.com/Kiyomi-Parents/OutCache
Author: LuCkEr-
Author-email: lucker@lucker.xyz
Project-URL: Bug Tracker, https://github.com/Kiyomi-Parents/OutCache/issues
Classifier: Programming Language :: Python :: 3
Classifier: License :: OSI Approved :: MIT License
Classifier: Operating System :: OS Independent
Requires-Python: >=3.6
License-File: LICENSE
